nxfvars/__init__.py
nxfvars/_params_handler.py
nxfvars/cli.py
nxfvars/execute.py
nxfvars/tests/__init__.py
nxfvars/tests/test_execute.py
nxfvars/tests/test_nxfvars.py
nxfvars/tests/testdata/notebook.ipynb
nxfvars/tests/testdata/notebook.py
nxfvars/tests/testdata/params1.yml
nxfvars/tests/testdata/params2.yml
nxfvars/tests/testdata/params_empty.yml
nxfvars-0.2.dist-info/entry_points.txt
nxfvars-0.2.dist-info/WHEEL
nxfvars-0.2.dist-info/METADATA
nxfvars-0.2.dist-info/RECORD
